fastapi_jwt/__init__.py
fastapi_jwt/jwt.py
fastapi_jwt-0.1.12.dist-info/LICENSE
fastapi_jwt-0.1.12.dist-info/METADATA
fastapi_jwt-0.1.12.dist-info/WHEEL
fastapi_jwt-0.1.12.dist-info/top_level.txt
fastapi_jwt-0.1.12.dist-info/RECORD
